gaugefixer/__init__.py
gaugefixer/docstrings.py
gaugefixer/encoder.py
gaugefixer/fixer.py
gaugefixer/models.py
gaugefixer/utils.py
gaugefixer_acordero-0.1.7.dist-info/licenses/LICENSE
gaugefixer_acordero-0.1.7.dist-info/METADATA
gaugefixer_acordero-0.1.7.dist-info/WHEEL
gaugefixer_acordero-0.1.7.dist-info/top_level.txt
gaugefixer_acordero-0.1.7.dist-info/RECORD
