Metadata-Version: 2.4
Name: gaugefixer-acordero
Version: 0.1.7
Summary: Gauge fixing tools
License: MIT License
Requires-Python: >=3.10
License-File: LICENSE
Requires-Dist: numpy
Requires-Dist: pandas
Requires-Dist: typeguard
Dynamic: license-file
